atcd/AtcdDBQueueTask.py
atcd/AtcdDeviceTimeoutTask.py
atcd/AtcdThriftHandlerTask.py
atcd/AtcdVService.py
atcd/__init__.py
atcd/access_manager.py
atcd/db_manager.py
atcd/idmanager.py
atcd/backends/__init__.py
atcd/backends/linux.py
atcd/scripts/__init__.py
atcd/scripts/runner.py
atcd/tools/test_secure_access.py
atcd-0.1.6.data/scripts/atcd
atcd-0.1.6.dist-info/DESCRIPTION.rst
atcd-0.1.6.dist-info/METADATA
atcd-0.1.6.dist-info/RECORD
atcd-0.1.6.dist-info/WHEEL
atcd-0.1.6.dist-info/metadata.json
atcd-0.1.6.dist-info/top_level.txt
