Metadata-Version: 2.0
Name: atcd
Version: 0.1.6
Summary: ATC Daemon
Home-page: https://github.com/facebook/augmented-traffic-control
Author: Emmanuel Bretelle
Author-email: chantra@fb.com
License: UNKNOWN
Platform: UNKNOWN
Classifier: Programming Language :: Python
Requires-Dist: atc-thrift
Requires-Dist: pyotp (==1.4.1)
Requires-Dist: pyroute2 (==0.3.3)
Requires-Dist: sparts (==0.7.1)
